odoo/addons/fieldservice_route_availability/README.rst
odoo/addons/fieldservice_route_availability/__init__.py
odoo/addons/fieldservice_route_availability/__manifest__.py
odoo/addons/fieldservice_route_availability/i18n/ca.po
odoo/addons/fieldservice_route_availability/i18n/es.po
odoo/addons/fieldservice_route_availability/i18n/fieldservice_route_availability.pot
odoo/addons/fieldservice_route_availability/i18n/it.po
odoo/addons/fieldservice_route_availability/i18n/pt_BR.po
odoo/addons/fieldservice_route_availability/models/__init__.py
odoo/addons/fieldservice_route_availability/models/fsm_blackout_day.py
odoo/addons/fieldservice_route_availability/models/fsm_order.py
odoo/addons/fieldservice_route_availability/models/fsm_route.py
odoo/addons/fieldservice_route_availability/readme/CONTRIBUTORS.md
odoo/addons/fieldservice_route_availability/readme/DESCRIPTION.md
odoo/addons/fieldservice_route_availability/readme/USAGE.md
odoo/addons/fieldservice_route_availability/static/description/icon.png
odoo/addons/fieldservice_route_availability/static/description/index.html
odoo/addons/fieldservice_route_availability/tests/__init__.py
odoo/addons/fieldservice_route_availability/tests/test_route_availability.py
odoo/addons/fieldservice_route_availability/views/fsm_blackout_day_templates.xml
odoo/addons/fieldservice_route_availability/views/fsm_route.xml
odoo_addon_fieldservice_route_availability-18.0.1.0.0.2.dist-info/METADATA
odoo_addon_fieldservice_route_availability-18.0.1.0.0.2.dist-info/WHEEL
odoo_addon_fieldservice_route_availability-18.0.1.0.0.2.dist-info/top_level.txt
odoo_addon_fieldservice_route_availability-18.0.1.0.0.2.dist-info/RECORD
