Metadata-Version: 2.1
Name: odoo-addon-fieldservice_route_availability
Version: 18.0.1.0.0.2
Requires-Python: >=3.10
Requires-Dist: odoo-addon-fieldservice_availability==18.0.*
Requires-Dist: odoo==18.0.*
Summary: Restricts blackout days for Scheduled Start (ETA) orders with the same date.
Home-page: https://github.com/OCA/field-service
License: AGPL-3
Author: APSL-Nagarro, Odoo Community Association (OCA)
Author-email: support@odoo-community.org
Classifier: Programming Language :: Python
Classifier: Framework :: Odoo
Classifier: Framework :: Odoo :: 18.0
Classifier: License :: OSI Approved :: GNU Affero General Public License v3
